{"cameraMode":{"drawMode":0,"name":"Shaded","section":"Shading Mode"},"sceneLighting":true,"audioPlay":false,"sceneViewState":{"showFog":true,"showMaterialUpdate":false,"showSkybox":true,"showFlares":true,"showImageEffects":true,"showParticleSystems":true},"in2DMode":false,"pivot":{"x":5.6714019775390629,"y":-0.38150882720947268,"z":124.14359283447266},"rotation":{"x":0.03695451468229294,"y":-0.713711678981781,"z":0.037685781717300418,"w":0.6984480619430542},"size":55.99369812011719,"orthographic":false}